tanmatsu/__init__.py
tanmatsu/debug.py
tanmatsu/draw.py
tanmatsu/geometry.py
tanmatsu/input.py
tanmatsu/output.py
tanmatsu/screenbuffer.py
tanmatsu/size.py
tanmatsu/style.py
tanmatsu/tanmatsu.py
tanmatsu/theme.py
tanmatsu/wctools.py
tanmatsu/widgets/__init__.py
tanmatsu/widgets/base.py
tanmatsu/widgets/box.py
tanmatsu/widgets/button.py
tanmatsu/widgets/container.py
tanmatsu/widgets/flexbox.py
tanmatsu/widgets/list.py
tanmatsu/widgets/scrollable.py
tanmatsu/widgets/tabbox.py
tanmatsu/widgets/textbox.py
tanmatsu/widgets/textlog.py
tanmatsu-0.1.1.dist-info/LICENSE.md
tanmatsu-0.1.1.dist-info/WHEEL
tanmatsu-0.1.1.dist-info/METADATA
tanmatsu-0.1.1.dist-info/RECORD
