Metadata-Version: 2.1
Name: tanmatsu
Version: 0.1.1
Summary: Declarative Terminal User Interface Library
Home-page: https://github.com/snowdrop4/tanmatsu
License: MIT
Author: snowdrop4
Author-email: 82846066+snowdrop4@users.noreply.github.com
Requires-Python: >=3.11,<4.0
Classifier: Environment :: Console
Classifier: License :: OSI Approved :: MIT License
Classifier: Operating System :: POSIX :: Linux
Classifier: Programming Language :: Python :: 3
Classifier: Topic :: Software Development :: User Interfaces
Classifier: Topic :: Terminals
Requires-Dist: parsy (>=1.3.0,<1.4.0)
Requires-Dist: tri.declarative (>=5.0,<6.0)
Requires-Dist: wcwidth (>=0.2,<0.3)
Project-URL: Documentation, https://tanmatsu.readthedocs.io/en/latest/
Project-URL: Repository, https://github.com/snowdrop4/tanmatsu
